mime_utils/__init__.py
mime_utils/oauth2user.py
mime_utils-0.1.1.dist-info/LICENSE.txt
mime_utils-0.1.1.dist-info/METADATA
mime_utils-0.1.1.dist-info/WHEEL
mime_utils-0.1.1.dist-info/top_level.txt
mime_utils-0.1.1.dist-info/RECORD
